hashed_list/__init__.py
hashed_list/hashed_list.py
hashed_list-1.0.5.dist-info/LICENSE
hashed_list-1.0.5.dist-info/METADATA
hashed_list-1.0.5.dist-info/WHEEL
hashed_list-1.0.5.dist-info/top_level.txt
hashed_list-1.0.5.dist-info/RECORD
