Metadata-Version: 2.1
Name: hashed-list
Version: 1.0.5
Summary: An auto-indexed Python List data structure with constant time .index() method
Home-page: https://github.com/imranariffin/hashed-list
Author: Imran Ariffin
Author-email: ariffin.imran@gmail.com
License: UNKNOWN
Project-URL: Bug Tracker, https://github.com/imranariffin/hashed-list/issues
Platform: UNKNOWN
Classifier: Programming Language :: Python :: 3
Classifier: License :: OSI Approved :: MIT License
Classifier: Operating System :: OS Independent
Requires-Python: >=3.5
License-File: LICENSE
